yaiv/__init__.py
yaiv/cell.py
yaiv/grep.py
yaiv/phonon.py
yaiv/plot.py
yaiv/spectrum.py
yaiv/utils.py
yaiv/defaults/__init__.py
yaiv/defaults/config.py
yaiv/defaults/extra_units.txt
yaiv-1.3.0.dist-info/licenses/LICENSE
yaiv-1.3.0.dist-info/METADATA
yaiv-1.3.0.dist-info/WHEEL
yaiv-1.3.0.dist-info/top_level.txt
yaiv-1.3.0.dist-info/RECORD
