Metadata-Version: 2.4
Name: yaiv
Version: 1.3.0
Summary: Yet another Ab Initio Visualizer with a variety of tools
Home-page: https://github.com/mgamigo/YAIV
Author: Martin Gutierrez-Amigo
Author-email: Martin Gutierrez-Amigo <martin.gutierrez.amigo@gmail.com>
Project-URL: Homepage, https://github.com/mgamigo/YAIV
Project-URL: Bug Tracker, https://github.com/mgamigo/YAIV/issues
Classifier: Programming Language :: Python :: 3
Classifier: Operating System :: OS Independent
Classifier: License :: OSI Approved :: GNU General Public License v3 (GPLv3)
Requires-Python: >=3.6
License-File: LICENSE
Requires-Dist: ipympl
Requires-Dist: pint
Requires-Dist: ase
Requires-Dist: spglib
Requires-Dist: scipy
Dynamic: author
Dynamic: home-page
Dynamic: license-file
Dynamic: requires-python
